ossh/__init__.py
ossh-0.1.0.dist-info/METADATA
ossh-0.1.0.dist-info/WHEEL
ossh-0.1.0.dist-info/entry_points.txt
ossh-0.1.0.dist-info/top_level.txt
ossh-0.1.0.dist-info/RECORD
