Metadata-Version: 2.1
Name: ossh
Version: 0.1.0
Summary: A ssh cli tool to make your ssh easy
Home-page: https://github.com/wangzewang/oak-ssh
Author: wangzewang
Author-email: wangzewang@outlook.com
License: UNKNOWN
Project-URL: Bug Reports, https://github.com/wangzewang/oak-ssh/issues
Project-URL: Say Thanks!, http://saythanks.io/to/wangzewang
Project-URL: Source, https://github.com/wangzewang/oak-ssh/
Keywords: ssh cli tool
Platform: UNKNOWN
Classifier: License :: OSI Approved :: MIT License
Classifier: Programming Language :: Python :: 3
Classifier: Programming Language :: Python :: 3.5
Classifier: Programming Language :: Python :: 3.6
Classifier: Programming Language :: Python :: 3.7
Requires-Python: >=3.5
